LICENSE
README.md
setup.py
sm4/__init__.py
sm4/base.py
sm4/compatibility.py
sm4/core.py
sm4.egg-info/PKG-INFO
sm4.egg-info/SOURCES.txt
sm4.egg-info/dependency_links.txt
sm4.egg-info/top_level.txt